{
  "changes": {
    "available": true,
    "evidence_score_points": 0.0,
    "market_score_points": 1.26,
    "sol_price_absolute": 0.87,
    "sol_price_pct": 0.01
  },
  "current_run": {
    "capital_flows_score": 48.47,
    "current_strength_score": 50.42,
    "data_cutoff_utc": "2026-07-19T23:59:59Z",
    "ecosystem_breadth_score": 60.96,
    "method_version": "1.0.0",
    "network_usage_score": 43.37,
    "price_strength_score": 52.86,
    "regime": "mixed",
    "regime_title": "Gemengd marktbeeld",
    "run_at_utc": "2026-07-20T10:56:11Z",
    "sol_price": 76.33,
    "support_score": 55.0
  },
  "drivers": [
    {
      "change_label": "licht veranderd",
      "comparison_status": "comparable",
      "contribution_delta": 0.75,
      "current_contribution": 23.79,
      "current_score": 52.86,
      "current_weight": 0.45,
      "key": "price_strength",
      "label": "Koerskracht",
      "previous_contribution": 23.04,
      "previous_score": 51.19,
      "previous_weight": 0.45,
      "score_delta": 1.67
    },
    {
      "change_label": "licht veranderd",
      "comparison_status": "comparable",
      "contribution_delta": 0.43,
      "current_contribution": 10.84,
      "current_score": 43.37,
      "current_weight": 0.25,
      "key": "network_usage",
      "label": "Netwerkgebruik",
      "previous_contribution": 10.41,
      "previous_score": 41.66,
      "previous_weight": 0.25,
      "score_delta": 1.71
    },
    {
      "change_label": "licht veranderd",
      "comparison_status": "comparable",
      "contribution_delta": -0.11,
      "current_contribution": 9.69,
      "current_score": 48.47,
      "current_weight": 0.2,
      "key": "capital_flows",
      "label": "Kapitaalstromen",
      "previous_contribution": 9.8,
      "previous_score": 48.99,
      "previous_weight": 0.2,
      "score_delta": -0.52
    },
    {
      "change_label": "licht veranderd",
      "comparison_status": "comparable",
      "contribution_delta": 0.19,
      "current_contribution": 6.1,
      "current_score": 60.96,
      "current_weight": 0.1,
      "key": "ecosystem_breadth",
      "label": "Ecosysteembreedte",
      "previous_contribution": 5.91,
      "previous_score": 59.13,
      "previous_weight": 0.1,
      "score_delta": 1.83
    }
  ],
  "generated_at_utc": "2026-07-20T10:56:11Z",
  "largest_changes": {
    "all_unchanged_message": null,
    "conclusion": "Per saldo veranderde het beeld nauwelijks sinds de vorige officiële run.",
    "negative": [
      {
        "change_label": "licht veranderd",
        "comparison_status": "comparable",
        "contribution_delta": -0.11,
        "current_contribution": 9.69,
        "current_score": 48.47,
        "current_weight": 0.2,
        "key": "capital_flows",
        "label": "Kapitaalstromen",
        "previous_contribution": 9.8,
        "previous_score": 48.99,
        "previous_weight": 0.2,
        "score_delta": -0.52
      }
    ],
    "negative_empty_message": null,
    "positive": [
      {
        "change_label": "licht veranderd",
        "comparison_status": "comparable",
        "contribution_delta": 0.19,
        "current_contribution": 6.1,
        "current_score": 60.96,
        "current_weight": 0.1,
        "key": "ecosystem_breadth",
        "label": "Ecosysteembreedte",
        "previous_contribution": 5.91,
        "previous_score": 59.13,
        "previous_weight": 0.1,
        "score_delta": 1.83
      },
      {
        "change_label": "licht veranderd",
        "comparison_status": "comparable",
        "contribution_delta": 0.43,
        "current_contribution": 10.84,
        "current_score": 43.37,
        "current_weight": 0.25,
        "key": "network_usage",
        "label": "Netwerkgebruik",
        "previous_contribution": 10.41,
        "previous_score": 41.66,
        "previous_weight": 0.25,
        "score_delta": 1.71
      }
    ],
    "positive_empty_message": null
  },
  "method_transitions": [],
  "previous_run": {
    "capital_flows_score": 48.99,
    "current_strength_score": 49.16,
    "data_cutoff_utc": "2026-07-18T23:59:59Z",
    "ecosystem_breadth_score": 59.13,
    "method_version": "1.0.0",
    "network_usage_score": 41.66,
    "price_strength_score": 51.19,
    "regime": "mixed",
    "regime_title": "Gemengd marktbeeld",
    "run_at_utc": "2026-07-19T09:55:22Z",
    "sol_price": 75.46,
    "support_score": 55.0
  },
  "schema_version": "1.1",
  "track_record": {
    "backtest_7d": {
      "brier_score": 0.2697,
      "brier_skill": -0.0355,
      "calibration_error": 0.1116,
      "directional_accuracy": 0.458,
      "prediction_count": 131
    },
    "backtest_metrics": {
      "7d": {
        "brier_score": 0.2697,
        "brier_skill": -0.0355,
        "calibration_error": 0.1116,
        "directional_accuracy": 0.458,
        "prediction_count": 131,
        "status": "Niet beter dan de basislijn."
      }
    },
    "backtest_status": "Niet beter dan de basislijn.",
    "calendar_span_days": 11,
    "current_method_version": "1.0.0",
    "evidence_status": "beperkt onderbouwd",
    "explanation": "Technische updates kunnen meerdere keren per datadag plaatsvinden. Alleen unieke, vooraf vastgelegde voorspellingen tellen mee als officieel signaal.",
    "first_prediction_at_utc": "2026-07-05T16:21:10Z",
    "first_run_at_utc": "2026-07-08T20:14:28Z",
    "forward_metrics": {},
    "forward_status": "Nog geen afgeronde publieke voorspellingen.",
    "last_prediction_at_utc": "2026-07-20T10:56:11Z",
    "latest_run_at_utc": "2026-07-20T10:56:11Z",
    "legacy_prediction_count": 0,
    "maturity_status": "Startfase",
    "method_version_count": 1,
    "method_versions": [
      "1.0.0"
    ],
    "next_maturity_threshold": 30,
    "official_signal_count": 16,
    "open_signal_count": 16,
    "prediction_count": 16,
    "production_run_count": 16,
    "quality_caps": [
      "Voorspelkwaliteit ≤ 0",
      "Breedte in ecosysteem telt beperkt mee en is nog experimenteel.",
      "RPC-netwerkcontext telt alleen actueel mee, niet in de backtest."
    ],
    "resolved_by_horizon": {},
    "resolved_outcome_count": 0,
    "technical_run_count": 16,
    "unique_prediction_days": 16
  },
  "warnings": [],
  "waterfall": {
    "available": true,
    "driver_delta_sum": 1.26,
    "end_score": 50.42,
    "reason_unavailable": null,
    "residual_delta": 0.0,
    "start_score": 49.16,
    "steps": [
      {
        "delta": 0.75,
        "direction": "positive",
        "end": 49.91,
        "key": "price_strength",
        "kind": "driver",
        "label": "Koerskracht",
        "start": 49.16
      },
      {
        "delta": 0.43,
        "direction": "positive",
        "end": 50.34,
        "key": "network_usage",
        "kind": "driver",
        "label": "Netwerkgebruik",
        "start": 49.91
      },
      {
        "delta": -0.11,
        "direction": "negative",
        "end": 50.23,
        "key": "capital_flows",
        "kind": "driver",
        "label": "Kapitaalstromen",
        "start": 50.34
      },
      {
        "delta": 0.19,
        "direction": "positive",
        "end": 50.42,
        "key": "ecosystem_breadth",
        "kind": "driver",
        "label": "Ecosysteembreedte",
        "start": 50.23
      }
    ],
    "summary": "De score bewoog vooral omhoog door koerskracht en omlaag door kapitaalstromen."
  },
  "what_would_change": [
    "SOL herwint duidelijke relatieve sterkte ten opzichte van BTC.",
    "Gebruik, DEX-volume en fees stijgen boven hun normale niveau.",
    "Stablecoinvoorraad en TVL beginnen duidelijk toe te nemen.",
    "De beweging versmalt naar minder Solana-ecosysteemtokens."
  ]
}
