{
  "generated_at_utc": "2026-07-24T10:22:34Z",
  "method_version": "1.0.0",
  "rows": [
    {
      "conclusion_stable": true,
      "k": 25,
      "weighting": "standard",
      "window_days": 730
    },
    {
      "conclusion_stable": true,
      "k": 40,
      "weighting": "standard",
      "window_days": 730
    },
    {
      "conclusion_stable": true,
      "k": 60,
      "weighting": "standard",
      "window_days": 730
    }
  ],
  "schema_version": "1.0",
  "summary": "De conclusie blijft bij de meeste redelijke instellingen gelijk in de demo-run."
}
